cannycam/__init__.py
cannycam/_version.py
cannycam/basecam.py
cannycam/cannycam.py
cannycam/cannyhaarcam.py
cannycam/haarcam.py
cannycam/util.py
cannycam/xmls/haarcascade_frontalface_default.xml
cannycam/xmls/haarcascade_fullbody.xml
cannycam/xmls/haarcascade_lowerbody.xml
cannycam/xmls/haarcascade_upperbody.xml
cannycam-0.0.5.dist-info/METADATA
cannycam-0.0.5.dist-info/RECORD
cannycam-0.0.5.dist-info/WHEEL
cannycam-0.0.5.dist-info/entry_points.txt
cannycam-0.0.5.dist-info/top_level.txt
