Metadata-Version: 2.1
Name: cannycam
Version: 0.0.5
Summary: A facial and anatomical recognition program
Home-page: http://github.com/cooltoast/CannyCam
Author: cooltoast
License: MIT
Platform: UNKNOWN
Classifier: Development Status :: 3 - Alpha
Classifier: License :: OSI Approved :: MIT License
Classifier: Programming Language :: Python :: 2.7
Classifier: Topic :: Scientific/Engineering :: Image Recognition
Requires-Dist: numpy (==1.16.2)
Requires-Dist: opencv-contrib-python (==4.1.0.25)
